{
  "organs": [
    {
      "id": "minpromtorg",
      "name": "Министерство промышленности и торговли Российской Федерации",
      "abbreviation": "Минпромторг России",
      "description": "Федеральный орган исполнительной власти, осуществляющий функции по выработке государственной политики и нормативно-правовому регулированию в сфере промышленного и оборонно-промышленного комплекса...",
      "system": "ministry",
      "structure": "government",
      "spheres": ["economic", "social"],
      "icon": "industry",
      "color": "#90EE90",
      "powers": ["НПА"],
      "file": "minpromtorg.html",
      "tags": ["промышленность", "торговля", "оборонный комплекс"],
      "website": "https://minpromtorg.gov.ru/"
    },
    {
      "id": "minfin",
      "name": "Министерство финансов Российской Федерации",
      "abbreviation": "Минфин России",
      "description": "Федеральный орган исполнительной власти, осуществляющий функции по выработке государственной политики и нормативно-правовому регулированию в сфере бюджетной, налоговой...",
      "system": "ministry",
      "structure": "government",
      "spheres": ["economic"],
      "icon": "money-bill-wave",
      "color": "#1013e3",
      "powers": ["НПА"],
      "file": "minfin.html",
      "tags": ["финансы", "бюджет", "налоги"],
      "website": "https://minfin.gov.ru/"
    }
    // Добавьте остальные 67 органов
  ],
  "metadata": {
    "total": 69,
    "lastUpdated": "2024-01-20"
  }
}
